LICENSE
simple_rss_reader/__init__.py
simple_rss_reader/exceptions.py
simple_rss_reader/reader.py
yet_another_simple_rss_parser-0.0.5.dist-info/LICENSE
yet_another_simple_rss_parser-0.0.5.dist-info/WHEEL
yet_another_simple_rss_parser-0.0.5.dist-info/METADATA
yet_another_simple_rss_parser-0.0.5.dist-info/RECORD
