Metadata-Version: 2.1
Name: yet-another-simple-rss-parser
Version: 0.0.5
Summary: Simple RSS reader/parser
Home-page: https://www.pypi.org/project/yet-another-simple-rss-parser/
License: MIT
Keywords: rss,parser
Author: Barak Bloch
Author-email: barak.bloch@gmail.com
Requires-Python: >=3.6,<4.0
Classifier: Environment :: Console
Classifier: License :: OSI Approved :: MIT License
Classifier: Operating System :: OS Independent
Classifier: Programming Language :: Python :: 3
Classifier: Programming Language :: Python :: 3.10
Classifier: Programming Language :: Python :: 3.6
Classifier: Programming Language :: Python :: 3.7
Classifier: Programming Language :: Python :: 3.8
Classifier: Programming Language :: Python :: 3.9
Classifier: Topic :: Software Development :: Libraries :: Python Modules
Requires-Dist: flake8 (>=3.7,<4.0)
Project-URL: Repository, https://github.com/barakbl/simple_rss_reader
